<?xml version="1.0" encoding="UTF-8"?>
<!-- Created with TexturePacker http://www.codeandweb.com/texturepacker-->
<!-- $TexturePacker:SmartUpdate:ae8897b8d5f3d65b32add6f1a5ced509:e0502dd35f61c63f2531ce23bf4c339c:8f3239cb2f4160886615eb4f6be191c7$ -->
<TextureAtlas imagePath="ICONS_ATLAS.png">
    <SubTexture name="COUNT_BUBBLE" x="119" y="2" rotated="true" width="7" height="8"/>
    <SubTexture name="DOT_SPRITE" x="109" y="20" width="7" height="4"/>
    <SubTexture name="ICON_ALERT" x="104" y="12" width="2" height="8"/>
    <SubTexture name="ICON_ARROW_LEFT" x="93" y="22" rotated="true" width="6" height="8" frameX="0" frameY="-1" frameWidth="8" frameHeight="8"/>
    <SubTexture name="ICON_ARROW_RIGHT" x="96" y="12" rotated="true" width="6" height="8" frameX="0" frameY="-1" frameWidth="8" frameHeight="8"/>
    <SubTexture name="ICON_BELL" x="13" y="20" width="8" height="8"/>
    <SubTexture name="ICON_BOOK_SMALL" x="49" y="2" width="8" height="8"/>
    <SubTexture name="ICON_CHECKMARK" x="23" y="20" width="8" height="8"/>
    <SubTexture name="ICON_CLOCK" x="59" y="2" width="8" height="8"/>
    <SubTexture name="ICON_COIN" x="109" y="26" width="4" height="4"/>
    <SubTexture name="ICON_CROP" x="69" y="2" width="8" height="8"/>
    <SubTexture name="ICON_GLOBE" x="79" y="2" width="8" height="8"/>
    <SubTexture name="ICON_GLOBE_STANDALONE" x="108" y="12" width="6" height="6"/>
    <SubTexture name="ICON_GOLD" x="89" y="2" width="8" height="8"/>
    <SubTexture name="ICON_HAMMER" x="99" y="2" width="8" height="8"/>
    <SubTexture name="ICON_IRON" x="2" y="20" width="9" height="8"/>
    <SubTexture name="ICON_LABOR" x="109" y="2" width="8" height="8"/>
    <SubTexture name="ICON_LEVEL_UP" x="38" y="12" width="8" height="8"/>
    <SubTexture name="ICON_MAP" x="33" y="22" width="8" height="8"/>
    <SubTexture name="ICON_MESSAGING" x="43" y="22" width="8" height="8"/>
    <SubTexture name="ICON_MINIMAP_ARROW_BLUE" x="101" y="22" rotated="true" width="6" height="8" frameX="0" frameY="-1" frameWidth="8" frameHeight="8"/>
    <SubTexture name="ICON_MINIMAP_ARROW_RED" x="96" y="12" rotated="true" width="6" height="8" frameX="0" frameY="-1" frameWidth="8" frameHeight="8"/>
    <SubTexture name="ICON_MINUS" x="118" y="20" rotated="true" width="2" height="6" frameX="0" frameY="-3" frameWidth="8" frameHeight="8"/>
    <SubTexture name="ICON_PAPER_SCROLL" x="2" y="2" width="16" height="16"/>
    <SubTexture name="ICON_PAPER_SCROLL_ALERT" x="20" y="2" width="16" height="16"/>
    <SubTexture name="ICON_PLUS" x="116" y="12" width="6" height="6" frameX="-1" frameY="-1" frameWidth="8" frameHeight="8"/>
    <SubTexture name="ICON_QUESTION" x="124" y="12" rotated="true" width="2" height="8" frameX="0" frameY="-5" frameWidth="8" frameHeight="8"/>
    <SubTexture name="ICON_RED_X" x="48" y="12" width="8" height="8"/>
    <SubTexture name="ICON_SHIELD" x="53" y="22" width="8" height="8"/>
    <SubTexture name="ICON_SINGLE_SWORD" x="58" y="12" width="8" height="8"/>
    <SubTexture name="ICON_STAR" x="63" y="22" width="8" height="8"/>
    <SubTexture name="ICON_STAR_EMPTY" x="68" y="12" width="8" height="8"/>
    <SubTexture name="ICON_STAR_HALF" x="73" y="22" width="8" height="8"/>
    <SubTexture name="ICON_SWORD" x="78" y="12" width="8" height="8"/>
    <SubTexture name="ICON_UNFRIEND" x="83" y="22" width="8" height="8"/>
    <SubTexture name="ICON_UPGRADE" x="88" y="12" width="6" height="8" frameX="-1" frameY="0" frameWidth="8" frameHeight="8"/>
    <SubTexture name="ICON_WOOD" x="38" y="2" width="9" height="8"/>
    <SubTexture name="MINIMAP_LARGE_CIRCLE_SPRITE" x="122" y="22" width="3" height="3"/>
    <SubTexture name="MINIMAP_SMALL_CIRCLE_SPRITE" x="115" y="28" width="2" height="2"/>
</TextureAtlas>
